tree_processing/__init__.py
tree_processing/traversal.py
tree_processing/actions/__init__.py
tree_processing/actions/filesystem.py
tree_processing/node_getters/__init__.py
tree_processing/node_getters/filesystem.py
tree_processing-0.4.1.dist-info/licenses/LICENSE.txt
tree_processing-0.4.1.dist-info/WHEEL
tree_processing-0.4.1.dist-info/METADATA
tree_processing-0.4.1.dist-info/RECORD
