Metadata-Version: 2.4
Name: tree_processing
Version: 0.4.1
Summary: Elegant composition of tree-traversal algorithms
Author-email: Karl Knechtel <zahlman@proton.me>
Requires-Python: >=3.6
License-Expression: MIT
Classifier: Development Status :: 3 - Alpha
Classifier: Intended Audience :: Developers
Classifier: Programming Language :: Python :: 3
Classifier: Programming Language :: Python :: 3.6
Classifier: Programming Language :: Python :: 3.7
Classifier: Programming Language :: Python :: 3.8
Classifier: Programming Language :: Python :: 3.9
Classifier: Programming Language :: Python :: 3.10
Classifier: Programming Language :: Python :: 3.11
Classifier: Programming Language :: Python :: 3.12
Classifier: Programming Language :: Python :: 3.13
Classifier: Programming Language :: Python :: 3.14
Classifier: Topic :: Software Development :: Libraries
License-File: LICENSE.txt
Project-URL: homepage, https://github.com/zahlman/tree_processing
